pypsoa/__init__.py
pypsoa/base.py
pypsoa-0.1.0.dist-info/LICENSE
pypsoa-0.1.0.dist-info/METADATA
pypsoa-0.1.0.dist-info/WHEEL
pypsoa-0.1.0.dist-info/top_level.txt
pypsoa-0.1.0.dist-info/RECORD
