Metadata-Version: 2.1
Name: pypsoa
Version: 0.1.0
Summary: A simple, zero-dependency Particle Swarm Optimization (PSO) library for Python.
Home-page: https://github.com/atasoglu/pypsoa
Author: Ahmet Atasoglu
Author-email: ahmetatasoglu98@gmail.com
License: MIT
Classifier: Programming Language :: Python :: 3
Classifier: Topic :: Scientific/Engineering :: Artificial Intelligence
Classifier: License :: OSI Approved :: MIT License
Classifier: Operating System :: OS Independent
Requires-Python: >=3.6
License-File: LICENSE
